README.md
setup.py
aioupnp/__init__.py
aioupnp/__main__.py
aioupnp/commands.py
aioupnp/constants.py
aioupnp/device.py
aioupnp/fault.py
aioupnp/gateway.py
aioupnp/interfaces.py
aioupnp/upnp.py
aioupnp/util.py
aioupnp.egg-info/PKG-INFO
aioupnp.egg-info/SOURCES.txt
aioupnp.egg-info/dependency_links.txt
aioupnp.egg-info/entry_points.txt
aioupnp.egg-info/requires.txt
aioupnp.egg-info/top_level.txt
aioupnp/protocols/__init__.py
aioupnp/protocols/m_search_patterns.py
aioupnp/protocols/multicast.py
aioupnp/protocols/scpd.py
aioupnp/protocols/ssdp.py
aioupnp/serialization/__init__.py
aioupnp/serialization/scpd.py
aioupnp/serialization/soap.py
aioupnp/serialization/ssdp.py
aioupnp/serialization/xml.py
tests/protocols/__init__.py
tests/protocols/test_multicast.py
tests/protocols/test_scpd.py
tests/protocols/test_ssdp.py
tests/serialization/__init__.py
tests/serialization/test_scpd.py
tests/serialization/test_soap.py
tests/serialization/test_ssdp.py