Metadata-Version: 2.1
Name: aioupnp
Version: 0.0.16
Summary: UPnP for asyncio
Home-page: https://github.com/lbryio/aioupnp
Author: Jack Robison
Author-email: jackrobison@lbry.com
License: MIT
Keywords: upnp asyncio ssdp network scpd
Platform: UNKNOWN
Classifier: Development Status :: 4 - Beta
Classifier: Intended Audience :: Developers
Classifier: License :: OSI Approved :: MIT License
Classifier: Operating System :: OS Independent
Classifier: Programming Language :: Python :: 3.7
Classifier: Programming Language :: Python :: 3.8
Classifier: Topic :: System :: Networking
Classifier: Topic :: Communications :: File Sharing
Provides-Extra: test
